lessdl/__init__.py
lessdl/utils.py
lessdl-0.0.1.dist-info/LICENSE
lessdl-0.0.1.dist-info/METADATA
lessdl-0.0.1.dist-info/WHEEL
lessdl-0.0.1.dist-info/top_level.txt
lessdl-0.0.1.dist-info/RECORD
