Metadata-Version: 2.1
Name: lessdl
Version: 0.0.1
Summary: Simple deep learning toolkit
Home-page: https://github.com/YongfeiYan/lessdl
Author: Yongfei Yan
Author-email: YongfeiYan <yongfeiyan@pku.edu.cn>
Project-URL: Homepage, https://github.com/YongfeiYan/lessdl
Project-URL: Bug Tracker, https://github.com/YongfeiYan/lessdl/issues
Classifier: Programming Language :: Python :: 3
Classifier: License :: OSI Approved :: MIT License
Classifier: Operating System :: OS Independent
Requires-Python: >=3.6
License-File: LICENSE
